/**
 *
 *  This code can be assembled with <a href="https://wiki.openjdk.java.net/display/CodeTools/asmtools">asmtools</a>
 *  using <code>asmtools jcoder *.jcoder</code> command line.
 *
 *  Test handling constant pool entries of unknown type.
 *
 *  Constant pool entry at index #10 has unknown tag 0xFF, not defined in JVMS.
 *  We should refuse to process this *.class file as we has no chance to correctly detect constant pool entry size
 *  and process rest of the class.
 *
 */
class java11/TestUnsupportedConstantPoolEntry {
  0xCAFEBABE;
  0; // minor version
  55; // version
  [] { // Constant Pool
    ; // first element is empty
    Method #3 #7; // #1
    class #8; // #2
    class #9; // #3
    Utf8 "<init>"; // #4
    Utf8 "()V"; // #5
    Utf8 "Code"; // #6
    NameAndType #4 #5; // #7
    Utf8 "java11/TestUnsupportedConstantPoolEntry"; // #8
    Utf8 "java/lang/Object"; // #9
    0xFF #3; // #10
  } // Constant Pool

  0x0021; // access
  #2;// this_cpx
  #3;// super_cpx

  [] { // Interfaces
  } // Interfaces

  [] { // Fields
  } // Fields

  [] { // Methods
    {  // method
      0x0001; // access
      #4; // name_index
      #5; // descriptor_index
      [] { // Attributes
        Attr(#6) { // Code
          1; // max_stack
          1; // max_locals
          Bytes[]{
            0x2AB70001B1;
          }
          [] { // Traps
          } // end Traps
          [] { // Attributes
          } // Attributes
        } // end Code
      } // Attributes
    }
  } // Methods

  [] { // Attributes
  } // Attributes
} // end class java11/TestUnsupportedConstantPoolEntry
