/**
 *
 *  This code can be assembled with <a href="https://wiki.openjdk.org/display/CodeTools/asmtools">asmtools</a>
 *  using <code>asmtools jcoder *.jcoder</code> command line.
 *
 *  Test reading constant pool with CONSTANT_Dynamic entry at index #2. Dynamic constant didn't used in the bytecode and thus 
 *  should not affect decompiled code correctness in any way.
 *
 */
class java11/TestDynamicConstantPoolEntry {
  0xCAFEBABE;
  0; // minor version
  55; // version
  [] { // Constant Pool
    ; // first element is empty
    String #29; // #1
    Dynamic 0s #25; // #2
    Field #35 #30; // #3
    Method #32 #36; // #4
    Method #22 #14; // #5
    Utf8 "TestDynamicConstantPoolEntry.jcoder"; // #6
    Utf8 "()V"; // #7
    Method #10 #9; // #8
    NameAndType #27 #13; // #9
    class #23; // #10
    Utf8 "Ljava/lang/Object;"; // #11
    Utf8 "<init>"; // #12
    Utf8 "(Ljava/lang/invoke/MethodHandles$Lookup;Ljava/lang/String;Ljava/lang/Class;)Ljava/lang/Object;"; // #13
    NameAndType #12 #7; // #14
    Utf8 "out"; // #15
    Utf8 "java/io/PrintStream"; // #16
    MethodHandle 6b #8; // #17
    Utf8 "SourceFile"; // #18
    class #31; // #19
    Utf8 "java/lang/System"; // #20
    Utf8 "(Ljava/lang/String;)V"; // #21
    class #34; // #22
    Utf8 "java/lang/invoke/ConstantBootstraps"; // #23
    Utf8 "println"; // #24
    NameAndType #27 #11; // #25
    Utf8 "Ljava/io/PrintStream;"; // #26
    Utf8 "nullConstant"; // #27
    Utf8 "BootstrapMethods"; // #28
    Utf8 "This class file contains constant pool entry of type CONSTANT_Dynamic, not used in the bytecode."; // #29
    NameAndType #15 #26; // #30
    Utf8 "java11/TestDynamicConstantPoolEntry"; // #31
    class #16; // #32
    Utf8 "main"; // #33
    Utf8 "java/lang/Object"; // #34
    class #20; // #35
    NameAndType #24 #21; // #36
    Utf8 "([Ljava/lang/String;)V"; // #37
    Utf8 "Code"; // #38
  } // Constant Pool

  0x0021; // access
  #19;// this_cpx
  #22;// super_cpx

  [] { // Interfaces
  } // Interfaces

  [] { // Fields
  } // Fields

  [] { // Methods
    {  // method
      0x0001; // access
      #12; // name_index
      #7; // descriptor_index
      [] { // Attributes
        Attr(#38) { // Code
          1; // max_stack
          1; // max_locals
          Bytes[]{
            0x2AB70005B1;
          }
          [] { // Traps
          } // end Traps
          [] { // Attributes
          } // Attributes
        } // end Code
      } // Attributes
    }
    ;
    {  // method
      0x0089; // access
      #33; // name_index
      #37; // descriptor_index
      [] { // Attributes
        Attr(#38) { // Code
          2; // max_stack
          1; // max_locals
          Bytes[]{
            0xB200031201B60004;
            0xB1;
          }
          [] { // Traps
          } // end Traps
          [] { // Attributes
          } // Attributes
        } // end Code
      } // Attributes
    }
  } // Methods

  [] { // Attributes
    Attr(#18) { // SourceFile
      #6;
    } // end SourceFile
    ;
    Attr(#28) { // BootstrapMethods
      [] { // bootstrap_methods
        {  //  bootstrap_method
          #17; // bootstrap_method_ref
          [] { // bootstrap_arguments
          }  //  bootstrap_arguments
        }  //  bootstrap_method
      }
    } // end BootstrapMethods
  } // Attributes
} // end class java11/TestDynamicConstantPoolEntry